README.md
__init__.py
emailaddressvalidator.py
setup.cfg
setup.py
emailaddressvalidator.egg-info/PKG-INFO
emailaddressvalidator.egg-info/SOURCES.txt
emailaddressvalidator.egg-info/dependency_links.txt
emailaddressvalidator.egg-info/top_level.txt