Metadata-Version: 1.0
Name: emailaddressvalidator
Version: 1.1
Summary: Little library for email format validation
Home-page: https://github.com/noris-network/emailaddressvalidator
Author: Roman Klesel
Author-email: roman.klesel@noris.de
License: UNKNOWN
Platform: UNKNOWN
